["```\r\n<dependency>\r\n    <groupId>com.okta.spring</groupId>\r\n    <artifactId>okta-spring-boot-starter</artifactId>\r\n    <version>1.4.0</version>\r\n</dependency>\r\n```","```\r\ncompile 'com.okta.spring:okta-spring-boot-starter:1.4.0'\r\n```","```\r\nokta.oauth2.issuer=https://dev-example123.okta.com/oauth2/default\r\nokta.oauth2.client-id=1230oaa4yncmaxaQ90ccJwl4x6\r\nokta.oauth2.client-secret=hjiyblEzgT0ItY91Ywcdzwa78oNhtrYqNklQ5vLzvruT123\r\nokta.oauth2.redirect-uri=/authorization-code/callback\r\n```","```\r\n@RestController\r\npublic class HomeController {\r\n    @GetMapping(\"/\")\r\n    public String home(@AuthenticationPrincipal OidcUser user) {\r\n        return \"Welcome, \"+ user.getFullName() + \"!\";\r\n    }\r\n}\r\n```","```\r\nmvn spring-boot:run\r\n```","```\r\n<dependency>\r\n    <groupId>com.okta.spring</groupId>\r\n    <artifactId>okta-spring-sdk</artifactId>\r\n    <version>1.4.0</version>\r\n</dependency>\r\n```","```\r\nokta.client.orgUrl=https://dev-example123.okta.com\r\nokta.client.token=00TVXDNx1e2FgvxP4jLlONbPMzrBDLwESSf9hZSvMI123\r\n```","```\r\n@RestController\r\npublic class AdminController {\r\n    @Autowired\r\n    public Client client;\r\n}\r\n```","```\r\npublic class AdminController {\r\n    // ...\r\n\r\n    @GetMapping(\"/users\") \r\n    public UserList getUsers() { \r\n        return client.listUsers(); \r\n    }\r\n}\r\n```","```\r\n{\r\n    \"dirty\":false,\r\n    \"propertyDescriptors\":{\r\n        \"items\":{\r\n            \"name\":\"items\",\r\n            \"type\":\"com.okta.sdk.resource.user.User\"\r\n        }\r\n    },\r\n    \"resourceHref\":\"/api/v1/users\",\r\n    \"currentPage\":{\r\n        \"items\":[\r\n            {\r\n                \"id\":\"00uanxiv7naevaEL14x6\",\r\n                \"profile\":{\r\n                    \"firstName\":\"Anshul\",\r\n                    \"lastName\":\"Bansal\",\r\n                    \"email\":\"[[email protected]](/web/20220628161334/https://www.baeldung.com/cdn-cgi/l/email-protection)\",\r\n                    // ...\r\n                },\r\n                // ...\r\n            },\r\n            { \r\n                \"id\":\"00uag6vugXMeBmXky4x6\", \r\n                \"profile\":{ \r\n                    \"firstName\":\"Ansh\", \r\n                    \"lastName\":\"Bans\", \r\n                    \"email\":\"[[email protected]](/web/20220628161334/https://www.baeldung.com/cdn-cgi/l/email-protection)\",\r\n                    // ... \r\n                }, \r\n                // ... \r\n            }\r\n        ]\r\n    },\r\n    \"empty\":false,\r\n    // ...\r\n}\r\n```","```\r\n@GetMapping(\"/user\")\r\npublic UserList searchUserByEmail(@RequestParam String query) {\r\n    return client.listUsers(query, null, null, null, null);\r\n}\r\n```","```\r\n{\r\n    \"dirty\":false,\r\n    \"propertyDescriptors\":{\r\n        \"items\":{\r\n            \"name\":\"items\",\r\n            \"type\":\"com.okta.sdk.resource.user.User\"\r\n        }\r\n    },\r\n    \"resourceHref\":\"/api/v1/users?q=ansh%40bans.com\",\r\n    \"currentPage\":{\r\n        \"items\":[\r\n            {\r\n                \"id\":\"00uag6vugXMeBmXky4x6\",\r\n                \"profile\":{\r\n                    \"firstName\":\"Ansh\",\r\n                    \"lastName\":\"Bans\",\r\n                    \"email\":\"[[email protected]](/web/20220628161334/https://www.baeldung.com/cdn-cgi/l/email-protection)\",\r\n                    // ...\r\n                },\r\n                // ...\r\n            }\r\n        ]\r\n    },\r\n    // ...\r\n}\r\n```","```\r\n@GetMapping(\"/createUser\")\r\npublic User createUser() {\r\n    char[] tempPassword = {'P','a','$','$','w','0','r','d'};\r\n    User user = UserBuilder.instance()\r\n        .setEmail(\"[[email protected]](/web/20220628161334/https://www.baeldung.com/cdn-cgi/l/email-protection)\")\r\n        .setFirstName(\"Norman\")\r\n        .setLastName(\"Lewis\")\r\n        .setPassword(tempPassword)\r\n        .setActive(true)\r\n        .buildAndCreate(client);\r\n    return user;\r\n}\r\n```","```\r\n{\r\n    \"id\": \"00uauveccPIYxQKUf4x6\",   \r\n    \"profile\": {\r\n        \"firstName\": \"Norman\",\r\n        \"lastName\": \"Lewis\",\r\n        \"email\": \"[[email protected]](/web/20220628161334/https://www.baeldung.com/cdn-cgi/l/email-protection)\"\r\n    },\r\n    \"credentials\": {\r\n        \"password\": {},\r\n        \"emails\": [\r\n            {\r\n                \"value\": \"[[email protected]](/web/20220628161334/https://www.baeldung.com/cdn-cgi/l/email-protection)\",\r\n                \"status\": \"VERIFIED\",\r\n                \"type\": \"PRIMARY\"\r\n            }\r\n        ],\r\n        // ...\r\n    },\r\n    \"_links\": {\r\n        \"resetPassword\": {\r\n            \"href\": \"https://dev-example123.okta.com/api/v1/users/00uauveccPIYxQKUf4x6/lifecycle/reset_password\",\r\n            \"method\": \"POST\"\r\n        },\r\n        // ...\r\n    }\r\n}\r\n```"]